portscannerali/__init__.py
portscannerali/scanner.py
portscannerali-0.1.dist-info/METADATA
portscannerali-0.1.dist-info/WHEEL
portscannerali-0.1.dist-info/top_level.txt
portscannerali-0.1.dist-info/RECORD
