Metadata-Version: 2.1
Name: portscannerali
Version: 0.1
Summary: A simple module to find open ports on a URL or IP address
Author: Zahid Ali
Author-email: zahid.arsol@gmail.com
Classifier: License :: OSI Approved :: MIT License
Classifier: Programming Language :: Python :: 3
Classifier: Programming Language :: Python :: 3.6
Classifier: Programming Language :: Python :: 3.7
Classifier: Programming Language :: Python :: 3.8
Classifier: Programming Language :: Python :: 3.9
Classifier: Programming Language :: Python :: 3.11
